LICENSE.txt
MANIFEST.in
README.md
setup.py
either/__init__.py
pyeither.egg-info/PKG-INFO
pyeither.egg-info/SOURCES.txt
pyeither.egg-info/dependency_links.txt
pyeither.egg-info/requires.txt
pyeither.egg-info/top_level.txt
tests/__init__.py
tests/test_either.py