Metadata-Version: 1.1
Name: pyeither
Version: 0.1.1
Summary: An implementation of Data.Either from Haskell in Python
Home-page: https://github.com/segfaultax/pyeither
Author: Michael-Keith Bernard
Author-email: mkbernard.dev@gmail.com
License: MIT
Keywords: either haskell data.either monad applicative functor
Platform: UNKNOWN
Classifier: Development Status :: 3 - Alpha
Classifier: Intended Audience :: Developers
Classifier: License :: OSI Approved :: MIT License
Classifier: Programming Language :: Python :: 2
Classifier: Programming Language :: Python :: 3
